{
    "GpCancel": [
        {
            "component_name": "GpExpressController",
            "label": "node controller",
            "type": "server",
            "sequence_id": 1,
            "dev_language": "Node.js",
            "dev_framework": "Express",
            "description": "controller for a NodeJs server application",
            "connector": true
        },
        {
            "component_name": "GpExpressService",
            "label": "node service",
            "type": "server",
            "sequence_id": 2,
            "dev_language": "Node.js",
            "dev_framework": "Express",
            "description": "service component for a NodeJS based application",
            "connector": true
        },
        {
            "component_name": "GpExpressDao",
            "label": "node dao",
            "type": "server",
            "sequence_id": 3,
            "dev_language": "Node.js",
            "dev_framework": "Express",
            "description": "dao component for a NodeJs based application",
            "connector": true
        },
        {
            "component_name": "GpAngularComponent",
            "label": "angular component",
            "type": "client",
            "sequence_id": 1,
            "dev_language": "java_script",
            "dev_framework": "Angular",
            "description": "component for Angular desktop",
            "connector": true
        },
        {
            "component_name": "GpAngularService",
            "label": "angular service",
            "type": "client",
            "sequence_id": 2,
            "dev_language": "java_script",
            "dev_framework": "Angular",
            "description": "service for Angular desktop",
            "connector": true
        },
        {
            "component_name": "GpIonicAngularComponent",
            "label": "angular component",
            "type": "client",
            "sequence_id": 1,
            "dev_language": "java_script",
            "dev_framework": "Ionic Angular",
            "description": "component for ionic Angular mobile",
            "connector": true
        },
        {
            "component_name": "GpIonicAngularService",
            "label": "angular service",
            "type": "client",
            "sequence_id": 2,
            "dev_language": "java_script",
            "dev_framework": "Ionic Angular",
            "description": "service for ionic Angular mobile",
            "connector": true
        }
    ],
    "GpCreate": [
        {
            "component_name": "GpExpressController",
            "label": "node controller",
            "type": "server",
            "sequence_id": 1,
            "dev_language": "Node.js",
            "dev_framework": "Express",
            "description": "controller for a NodeJs server application",
            "connector": true
        },
        {
            "component_name": "GpExpressService",
            "label": "node service",
            "type": "server",
            "sequence_id": 2,
            "dev_language": "Node.js",
            "dev_framework": "Express",
            "description": "service component for a NodeJS based application",
            "connector": true
        },
        {
            "component_name": "GpExpressDao",
            "label": "node dao",
            "type": "server",
            "sequence_id": 3,
            "dev_language": "Node.js",
            "dev_framework": "Express",
            "description": "dao component for a NodeJs based application",
            "connector": true
        },
        {
            "component_name": "GpAngularComponent",
            "label": "angular component",
            "type": "client",
            "sequence_id": 1,
            "dev_language": "java_script",
            "dev_framework": "Angular",
            "description": "component for Angular desktop",
            "connector": true
        },
        {
            "component_name": "GpAngularService",
            "label": "angular service",
            "type": "client",
            "sequence_id": 2,
            "dev_language": "java_script",
            "dev_framework": "Angular",
            "description": "service for Angular desktop",
            "connector": true
        },
        {
            "component_name": "GpIonicAngularComponent",
            "label": "angular component",
            "type": "client",
            "sequence_id": 1,
            "dev_language": "java_script",
            "dev_framework": "Ionic Angular",
            "description": "component for ionic Angular mobile",
            "connector": true
        },
        {
            "component_name": "GpIonicAngularService",
            "label": "angular service",
            "type": "client",
            "sequence_id": 2,
            "dev_language": "java_script",
            "dev_framework": "Ionic Angular",
            "description": "service for ionic Angular mobile",
            "connector": true
        }
    ],
    "GpCustom": [
        {
            "component_name": "GpExpressController",
            "label": "node controller",
            "type": "server",
            "sequence_id": 1,
            "dev_language": "Node.js",
            "dev_framework": "Express",
            "description": "controller for a NodeJs server application",
            "connector": true
        },
        {
            "component_name": "GpExpressService",
            "label": "node service",
            "type": "server",
            "sequence_id": 2,
            "dev_language": "Node.js",
            "dev_framework": "Express",
            "description": "service component for a NodeJS based application",
            "connector": true
        },
        {
            "component_name": "GpExpressDao",
            "label": "node dao",
            "type": "server",
            "sequence_id": 3,
            "dev_language": "Node.js",
            "dev_framework": "Express",
            "description": "dao component for a NodeJs based application",
            "connector": true
        },
        {
            "component_name": "GpAngularComponent",
            "label": "angular component",
            "type": "client",
            "sequence_id": 1,
            "dev_language": "java_script",
            "dev_framework": "Angular",
            "description": "component for Angular desktop",
            "connector": true
        },
        {
            "component_name": "GpAngularService",
            "label": "angular service",
            "type": "client",
            "sequence_id": 2,
            "dev_language": "java_script",
            "dev_framework": "Angular",
            "description": "service for Angular desktop",
            "connector": true
        },
        {
            "component_name": "GpIonicAngularComponent",
            "label": "angular component",
            "type": "client",
            "sequence_id": 1,
            "dev_language": "java_script",
            "dev_framework": "Ionic Angular",
            "description": "component for ionic Angular mobile",
            "connector": true
        },
        {
            "component_name": "GpIonicAngularService",
            "label": "angular service",
            "type": "client",
            "sequence_id": 2,
            "dev_language": "java_script",
            "dev_framework": "Ionic Angular",
            "description": "service for ionic Angular mobile",
            "connector": true
        }
    ],
    "GpCreateRelationship": [
        {
            "component_name": "GpExpressController",
            "label": "node controller",
            "type": "server",
            "sequence_id": 1,
            "dev_language": "Node.js",
            "dev_framework": "Express",
            "description": "controller for a NodeJs server application",
            "connector": true
        },
        {
            "component_name": "GpExpressService",
            "label": "node service",
            "type": "server",
            "sequence_id": 2,
            "dev_language": "Node.js",
            "dev_framework": "Express",
            "description": "service component for a NodeJS based application",
            "connector": true
        },
        {
            "component_name": "GpExpressDao",
            "label": "node dao",
            "type": "server",
            "sequence_id": 3,
            "dev_language": "Node.js",
            "dev_framework": "Express",
            "description": "dao component for a NodeJs based application",
            "connector": true
        }
    ],
    "GpDelete": [
        {
            "component_name": "GpExpressController",
            "label": "node controller",
            "type": "server",
            "sequence_id": 1,
            "dev_language": "Node.js",
            "dev_framework": "Express",
            "description": "controller for a NodeJs server application",
            "connector": true
        },
        {
            "component_name": "GpExpressService",
            "label": "node service",
            "type": "server",
            "sequence_id": 2,
            "dev_language": "Node.js",
            "dev_framework": "Express",
            "description": "service component for a NodeJS based application",
            "connector": true
        },
        {
            "component_name": "GpExpressDao",
            "label": "node dao",
            "type": "server",
            "sequence_id": 3,
            "dev_language": "Node.js",
            "dev_framework": "Express",
            "description": "dao component for a NodeJs based application",
            "connector": true
        },
        {
            "component_name": "GpAngularComponent",
            "label": "angular component",
            "type": "client",
            "sequence_id": 1,
            "dev_language": "java_script",
            "dev_framework": "Angular",
            "description": "component for Angular desktop",
            "connector": true
        },
        {
            "component_name": "GpAngularService",
            "label": "angular service",
            "type": "client",
            "sequence_id": 2,
            "dev_language": "java_script",
            "dev_framework": "Angular",
            "description": "service for Angular desktop",
            "connector": true
        },
        {
            "component_name": "GpIonicAngularComponent",
            "label": "angular component",
            "type": "client",
            "sequence_id": 1,
            "dev_language": "java_script",
            "dev_framework": "Ionic Angular",
            "description": "component for ionic Angular mobile",
            "connector": true
        },
        {
            "component_name": "GpIonicAngularService",
            "label": "angular service",
            "type": "client",
            "sequence_id": 2,
            "dev_language": "java_script",
            "dev_framework": "Ionic Angular",
            "description": "service for ionic Angular mobile",
            "connector": true
        }
    ],
    "GpDeleteByParentId": [
        {
            "component_name": "GpExpressController",
            "label": "node controller",
            "type": "server",
            "sequence_id": 1,
            "dev_language": "Node.js",
            "dev_framework": "Express",
            "description": "controller for a NodeJs server application",
            "connector": true
        },
        {
            "component_name": "GpExpressService",
            "label": "node service",
            "type": "server",
            "sequence_id": 2,
            "dev_language": "Node.js",
            "dev_framework": "Express",
            "description": "service component for a NodeJS based application",
            "connector": true
        },
        {
            "component_name": "GpExpressDao",
            "label": "node dao",
            "type": "server",
            "sequence_id": 3,
            "dev_language": "Node.js",
            "dev_framework": "Express",
            "description": "dao component for a NodeJs based application",
            "connector": true
        }
    ],
    "GpDeleteNounRelationship": [
        {
            "component_name": "GpExpressController",
            "label": "node controller",
            "type": "server",
            "sequence_id": 1,
            "dev_language": "Node.js",
            "dev_framework": "Express",
            "description": "controller for a NodeJs server application",
            "connector": true
        },
        {
            "component_name": "GpExpressService",
            "label": "node service",
            "type": "server",
            "sequence_id": 2,
            "dev_language": "Node.js",
            "dev_framework": "Express",
            "description": "service component for a NodeJS based application",
            "connector": true
        },
        {
            "component_name": "GpExpressDao",
            "label": "node dao",
            "type": "server",
            "sequence_id": 3,
            "dev_language": "Node.js",
            "dev_framework": "Express",
            "description": "dao component for a NodeJs based application",
            "connector": true
        }
    ],
    "GpDeleteNounByRelation": [
        {
            "component_name": "GpExpressController",
            "label": "node controller",
            "type": "server",
            "sequence_id": 1,
            "dev_language": "Node.js",
            "dev_framework": "Express",
            "description": "controller for a NodeJs server application",
            "connector": true
        },
        {
            "component_name": "GpExpressService",
            "label": "node service",
            "type": "server",
            "sequence_id": 2,
            "dev_language": "Node.js",
            "dev_framework": "Express",
            "description": "service component for a NodeJS based application",
            "connector": true
        },
        {
            "component_name": "GpExpressDao",
            "label": "node dao",
            "type": "server",
            "sequence_id": 3,
            "dev_language": "Node.js",
            "dev_framework": "Express",
            "description": "dao component for a NodeJs based application",
            "connector": true
        }
    ],
    "GpGetAllValues": [
        {
            "component_name": "GpExpressController",
            "label": "node controller",
            "type": "server",
            "sequence_id": 1,
            "dev_language": "Node.js",
            "dev_framework": "Express",
            "description": "controller for a NodeJs server application",
            "connector": true
        },
        {
            "component_name": "GpExpressService",
            "label": "node service",
            "type": "server",
            "sequence_id": 2,
            "dev_language": "Node.js",
            "dev_framework": "Express",
            "description": "service component for a NodeJS based application",
            "connector": true
        },
        {
            "component_name": "GpExpressDao",
            "label": "node dao",
            "type": "server",
            "sequence_id": 3,
            "dev_language": "Node.js",
            "dev_framework": "Express",
            "description": "dao component for a NodeJs based application",
            "connector": true
        },
        {
            "component_name": "GpAngularComponent",
            "label": "angular component",
            "type": "client",
            "sequence_id": 1,
            "dev_language": "java_script",
            "dev_framework": "Angular",
            "description": "component for Angular desktop",
            "connector": true
        },
        {
            "component_name": "GpAngularService",
            "label": "angular service",
            "type": "client",
            "sequence_id": 2,
            "dev_language": "java_script",
            "dev_framework": "Angular",
            "description": "service for Angular desktop",
            "connector": true
        },
        {
            "component_name": "GpIonicAngularComponent",
            "label": "angular component",
            "type": "client",
            "sequence_id": 1,
            "dev_language": "java_script",
            "dev_framework": "Ionic Angular",
            "description": "component for ionic Angular mobile",
            "connector": true
        },
        {
            "component_name": "GpIonicAngularService",
            "label": "angular service",
            "type": "client",
            "sequence_id": 2,
            "dev_language": "java_script",
            "dev_framework": "Ionic Angular",
            "description": "service for ionic Angular mobile",
            "connector": true
        }
    ],
    "GpGetNounById": [
        {
            "component_name": "GpExpressController",
            "label": "node controller",
            "type": "server",
            "sequence_id": 1,
            "dev_language": "Node.js",
            "dev_framework": "Express",
            "description": "controller for a NodeJs server application",
            "connector": true
        },
        {
            "component_name": "GpExpressService",
            "label": "node service",
            "type": "server",
            "sequence_id": 2,
            "dev_language": "Node.js",
            "dev_framework": "Express",
            "description": "service component for a NodeJS based application",
            "connector": true
        },
        {
            "component_name": "GpExpressDao",
            "label": "node dao",
            "type": "server",
            "sequence_id": 3,
            "dev_language": "Node.js",
            "dev_framework": "Express",
            "description": "dao component for a NodeJs based application",
            "connector": true
        },
        {
            "component_name": "GpAngularComponent",
            "label": "angular component",
            "type": "client",
            "sequence_id": 1,
            "dev_language": "java_script",
            "dev_framework": "Angular",
            "description": "component for Angular desktop",
            "connector": true
        },
        {
            "component_name": "GpAngularService",
            "label": "angular service",
            "type": "client",
            "sequence_id": 2,
            "dev_language": "java_script",
            "dev_framework": "Angular",
            "description": "service for Angular desktop",
            "connector": true
        },
        {
            "component_name": "GpIonicAngularComponent",
            "label": "angular component",
            "type": "client",
            "sequence_id": 1,
            "dev_language": "java_script",
            "dev_framework": "Ionic Angular",
            "description": "component for ionic Angular mobile",
            "connector": true
        },
        {
            "component_name": "GpIonicAngularService",
            "label": "angular service",
            "type": "client",
            "sequence_id": 2,
            "dev_language": "java_script",
            "dev_framework": "Ionic Angular",
            "description": "service for ionic Angular mobile",
            "connector": true
        }
    ],
    "GpGetNounByParentId": [
        {
            "component_name": "GpExpressController",
            "label": "node controller",
            "type": "server",
            "sequence_id": 1,
            "dev_language": "Node.js",
            "dev_framework": "Express",
            "description": "controller for a NodeJs server application",
            "connector": true
        },
        {
            "component_name": "GpExpressService",
            "label": "node service",
            "type": "server",
            "sequence_id": 2,
            "dev_language": "Node.js",
            "dev_framework": "Express",
            "description": "service component for a NodeJS based application",
            "connector": true
        },
        {
            "component_name": "GpExpressDao",
            "label": "node dao",
            "type": "server",
            "sequence_id": 3,
            "dev_language": "Node.js",
            "dev_framework": "Express",
            "description": "dao component for a NodeJs based application",
            "connector": true
        }
    ],
    "GpGetNounByRelation": [
        {
            "component_name": "GpExpressController",
            "label": "node controller",
            "type": "server",
            "sequence_id": 1,
            "dev_language": "Node.js",
            "dev_framework": "Express",
            "description": "controller for a NodeJs server application",
            "connector": true
        },
        {
            "component_name": "GpExpressService",
            "label": "node service",
            "type": "server",
            "sequence_id": 2,
            "dev_language": "Node.js",
            "dev_framework": "Express",
            "description": "service component for a NodeJS based application",
            "connector": true
        },
        {
            "component_name": "GpExpressDao",
            "label": "node dao",
            "type": "server",
            "sequence_id": 3,
            "dev_language": "Node.js",
            "dev_framework": "Express",
            "description": "dao component for a NodeJs based application",
            "connector": true
        }
    ],
    "GpGetNounByRelationship": [
        {
            "component_name": "GpExpressController",
            "label": "node controller",
            "type": "server",
            "sequence_id": 1,
            "dev_language": "Node.js",
            "dev_framework": "Express",
            "description": "controller for a NodeJs server application",
            "connector": true
        },
        {
            "component_name": "GpExpressService",
            "label": "node service",
            "type": "server",
            "sequence_id": 2,
            "dev_language": "Node.js",
            "dev_framework": "Express",
            "description": "service component for a NodeJS based application",
            "connector": true
        },
        {
            "component_name": "GpExpressDao",
            "label": "node dao",
            "type": "server",
            "sequence_id": 3,
            "dev_language": "Node.js",
            "dev_framework": "Express",
            "description": "dao component for a NodeJs based application",
            "connector": true
        }
    ],
    "GpGetNounFromRelation": [
        {
            "component_name": "GpExpressController",
            "label": "node controller",
            "type": "server",
            "sequence_id": 1,
            "dev_language": "Node.js",
            "dev_framework": "Express",
            "description": "controller for a NodeJs server application",
            "connector": true
        },
        {
            "component_name": "GpExpressService",
            "label": "node service",
            "type": "server",
            "sequence_id": 2,
            "dev_language": "Node.js",
            "dev_framework": "Express",
            "description": "service component for a NodeJS based application",
            "connector": true
        },
        {
            "component_name": "GpExpressDao",
            "label": "node dao",
            "type": "server",
            "sequence_id": 3,
            "dev_language": "Node.js",
            "dev_framework": "Express",
            "description": "dao component for a NodeJs based application",
            "connector": true
        }
    ],
    "GpRecordVideo": [
        {
            "component_name": "GpExpressController",
            "label": "node controller",
            "type": "server",
            "sequence_id": 1,
            "dev_language": "Node.js",
            "dev_framework": "Express",
            "description": "controller for a NodeJs server application",
            "connector": true
        },
        {
            "component_name": "GpExpressService",
            "label": "node service",
            "type": "server",
            "sequence_id": 2,
            "dev_language": "Node.js",
            "dev_framework": "Express",
            "description": "service component for a NodeJS based application",
            "connector": true
        },
        {
            "component_name": "GpExpressDao",
            "label": "node dao",
            "type": "server",
            "sequence_id": 3,
            "dev_language": "Node.js",
            "dev_framework": "Express",
            "description": "dao component for a NodeJs based application",
            "connector": true
        },
        {
            "component_name": "GpAngularComponent",
            "label": "angular component",
            "type": "client",
            "sequence_id": 1,
            "dev_language": "java_script",
            "dev_framework": "Angular",
            "description": "component for Angular desktop",
            "connector": true
        },
        {
            "component_name": "GpAngularService",
            "label": "angular service",
            "type": "client",
            "sequence_id": 2,
            "dev_language": "java_script",
            "dev_framework": "Angular",
            "description": "service for Angular desktop",
            "connector": true
        },
        {
            "component_name": "GpIonicAngularComponent",
            "label": "angular component",
            "type": "client",
            "sequence_id": 1,
            "dev_language": "java_script",
            "dev_framework": "Ionic Angular",
            "description": "component for ionic Angular mobile",
            "connector": true
        },
        {
            "component_name": "GpIonicAngularService",
            "label": "angular service",
            "type": "client",
            "sequence_id": 2,
            "dev_language": "java_script",
            "dev_framework": "Ionic Angular",
            "description": "service for ionic Angular mobile",
            "connector": true
        }
    ],
    "GpSearch": [
        {
            "component_name": "GpExpressController",
            "label": "node controller",
            "type": "server",
            "sequence_id": 1,
            "dev_language": "Node.js",
            "dev_framework": "Express",
            "description": "controller for a NodeJs server application",
            "connector": true
        },
        {
            "component_name": "GpExpressService",
            "label": "node service",
            "type": "server",
            "sequence_id": 2,
            "dev_language": "Node.js",
            "dev_framework": "Express",
            "description": "service component for a NodeJS based application",
            "connector": true
        },
        {
            "component_name": "GpExpressDao",
            "label": "node dao",
            "type": "server",
            "sequence_id": 3,
            "dev_language": "Node.js",
            "dev_framework": "Express",
            "description": "dao component for a NodeJs based application",
            "connector": true
        },
        {
            "component_name": "GpAngularComponent",
            "label": "angular component",
            "type": "client",
            "sequence_id": 1,
            "dev_language": "java_script",
            "dev_framework": "Angular",
            "description": "component for Angular desktop",
            "connector": true
        },
        {
            "component_name": "GpAngularService",
            "label": "angular service",
            "type": "client",
            "sequence_id": 2,
            "dev_language": "java_script",
            "dev_framework": "Angular",
            "description": "service for Angular desktop",
            "connector": true
        },
        {
            "component_name": "GpIonicAngularComponent",
            "label": "angular component",
            "type": "client",
            "sequence_id": 1,
            "dev_language": "java_script",
            "dev_framework": "Ionic Angular",
            "description": "component for ionic Angular mobile",
            "connector": true
        },
        {
            "component_name": "GpIonicAngularService",
            "label": "angular service",
            "type": "client",
            "sequence_id": 2,
            "dev_language": "java_script",
            "dev_framework": "Ionic Angular",
            "description": "service for ionic Angular mobile",
            "connector": true
        }
    ],
    "GpSearchDetail": [
        {
            "component_name": "GpExpressController",
            "label": "node controller",
            "type": "server",
            "sequence_id": 1,
            "dev_language": "Node.js",
            "dev_framework": "Express",
            "description": "controller for a NodeJs server application",
            "connector": true
        },
        {
            "component_name": "GpExpressService",
            "label": "node service",
            "type": "server",
            "sequence_id": 2,
            "dev_language": "Node.js",
            "dev_framework": "Express",
            "description": "service component for a NodeJS based application",
            "connector": true
        },
        {
            "component_name": "GpExpressDao",
            "label": "node dao",
            "type": "server",
            "sequence_id": 3,
            "dev_language": "Node.js",
            "dev_framework": "Express",
            "description": "dao component for a NodeJs based application",
            "connector": true
        },
        {
            "component_name": "GpAngularComponent",
            "label": "angular component",
            "type": "client",
            "sequence_id": 1,
            "dev_language": "java_script",
            "dev_framework": "Angular",
            "description": "component for Angular desktop",
            "connector": true
        },
        {
            "component_name": "GpAngularService",
            "label": "angular service",
            "type": "client",
            "sequence_id": 2,
            "dev_language": "java_script",
            "dev_framework": "Angular",
            "description": "service for Angular desktop",
            "connector": true
        },
        {
            "component_name": "GpIonicAngularComponent",
            "label": "angular component",
            "type": "client",
            "sequence_id": 1,
            "dev_language": "java_script",
            "dev_framework": "Ionic Angular",
            "description": "component for ionic Angular mobile",
            "connector": true
        },
        {
            "component_name": "GpIonicAngularService",
            "label": "angular service",
            "type": "client",
            "sequence_id": 2,
            "dev_language": "java_script",
            "dev_framework": "Ionic Angular",
            "description": "service for ionic Angular mobile",
            "connector": true
        }
    ],
    "GpSearchForUpdate": [
        {
            "component_name": "GpExpressController",
            "label": "node controller",
            "type": "server",
            "sequence_id": 1,
            "dev_language": "Node.js",
            "dev_framework": "Express",
            "description": "controller for a NodeJs server application",
            "connector": true
        },
        {
            "component_name": "GpExpressService",
            "label": "node service",
            "type": "server",
            "sequence_id": 2,
            "dev_language": "Node.js",
            "dev_framework": "Express",
            "description": "service component for a NodeJS based application",
            "connector": true
        },
        {
            "component_name": "GpExpressDao",
            "label": "node dao",
            "type": "server",
            "sequence_id": 3,
            "dev_language": "Node.js",
            "dev_framework": "Express",
            "description": "dao component for a NodeJs based application",
            "connector": true
        },
        {
            "component_name": "GpAngularComponent",
            "label": "angular component",
            "type": "client",
            "sequence_id": 1,
            "dev_language": "java_script",
            "dev_framework": "Angular",
            "description": "component for Angular desktop",
            "connector": true
        },
        {
            "component_name": "GpAngularService",
            "label": "angular service",
            "type": "client",
            "sequence_id": 2,
            "dev_language": "java_script",
            "dev_framework": "Angular",
            "description": "service for Angular desktop",
            "connector": true
        },
        {
            "component_name": "GpIonicAngularComponent",
            "label": "angular component",
            "type": "client",
            "sequence_id": 1,
            "dev_language": "java_script",
            "dev_framework": "Ionic Angular",
            "description": "component for ionic Angular mobile",
            "connector": true
        },
        {
            "component_name": "GpIonicAngularService",
            "label": "angular service",
            "type": "client",
            "sequence_id": 2,
            "dev_language": "java_script",
            "dev_framework": "Ionic Angular",
            "description": "service for ionic Angular mobile",
            "connector": true
        }
    ],
    "GpTakePhoto": [
        {
            "component_name": "GpExpressController",
            "label": "node controller",
            "type": "server",
            "sequence_id": 1,
            "dev_language": "Node.js",
            "dev_framework": "Express",
            "description": "controller for a NodeJs server application",
            "connector": true
        },
        {
            "component_name": "GpExpressService",
            "label": "node service",
            "type": "server",
            "sequence_id": 2,
            "dev_language": "Node.js",
            "dev_framework": "Express",
            "description": "service component for a NodeJS based application",
            "connector": true
        },
        {
            "component_name": "GpExpressDao",
            "label": "node dao",
            "type": "server",
            "sequence_id": 3,
            "dev_language": "Node.js",
            "dev_framework": "Express",
            "description": "dao component for a NodeJs based application",
            "connector": true
        },
        {
            "component_name": "GpAngularComponent",
            "label": "angular component",
            "type": "client",
            "sequence_id": 1,
            "dev_language": "java_script",
            "dev_framework": "Angular",
            "description": "component for Angular desktop",
            "connector": true
        },
        {
            "component_name": "GpAngularService",
            "label": "angular service",
            "type": "client",
            "sequence_id": 2,
            "dev_language": "java_script",
            "dev_framework": "Angular",
            "description": "service for Angular desktop",
            "connector": true
        },
        {
            "component_name": "GpIonicAngularComponent",
            "label": "angular component",
            "type": "client",
            "sequence_id": 1,
            "dev_language": "java_script",
            "dev_framework": "Ionic Angular",
            "description": "component for ionic Angular mobile",
            "connector": true
        },
        {
            "component_name": "GpIonicAngularService",
            "label": "angular service",
            "type": "client",
            "sequence_id": 2,
            "dev_language": "java_script",
            "dev_framework": "Ionic Angular",
            "description": "service for ionic Angular mobile",
            "connector": true
        }
    ],
    "GpUpdate": [
        {
            "component_name": "GpExpressController",
            "label": "node controller",
            "type": "server",
            "sequence_id": 1,
            "dev_language": "Node.js",
            "dev_framework": "Express",
            "description": "controller for a NodeJs server application",
            "connector": true
        },
        {
            "component_name": "GpExpressService",
            "label": "node service",
            "type": "server",
            "sequence_id": 2,
            "dev_language": "Node.js",
            "dev_framework": "Express",
            "description": "service component for a NodeJS based application",
            "connector": true
        },
        {
            "component_name": "GpExpressDao",
            "label": "node dao",
            "type": "server",
            "sequence_id": 3,
            "dev_language": "Node.js",
            "dev_framework": "Express",
            "description": "dao component for a NodeJs based application",
            "connector": true
        },
        {
            "component_name": "GpAngularComponent",
            "label": "angular component",
            "type": "client",
            "sequence_id": 1,
            "dev_language": "java_script",
            "dev_framework": "Angular",
            "description": "component for Angular desktop",
            "connector": true
        },
        {
            "component_name": "GpAngularService",
            "label": "angular service",
            "type": "client",
            "sequence_id": 2,
            "dev_language": "java_script",
            "dev_framework": "Angular",
            "description": "service for Angular desktop",
            "connector": true
        },
        {
            "component_name": "GpIonicAngularComponent",
            "label": "angular component",
            "type": "client",
            "sequence_id": 1,
            "dev_language": "java_script",
            "dev_framework": "Ionic Angular",
            "description": "component for ionic Angular mobile",
            "connector": true
        },
        {
            "component_name": "GpIonicAngularService",
            "label": "angular service",
            "type": "client",
            "sequence_id": 2,
            "dev_language": "java_script",
            "dev_framework": "Ionic Angular",
            "description": "service for ionic Angular mobile",
            "connector": true
        }
    ],
    "GpFileUpload": [
        {
            "component_name": "GpExpressController",
            "label": "node controller",
            "type": "server",
            "sequence_id": 1,
            "dev_language": "Node.js",
            "dev_framework": "Express",
            "description": "controller for a NodeJs server application",
            "connector": true
        },
        {
            "component_name": "GpExpressService",
            "label": "node service",
            "type": "server",
            "sequence_id": 2,
            "dev_language": "Node.js",
            "dev_framework": "Express",
            "description": "service component for a NodeJS based application",
            "connector": true
        },
        {
            "component_name": "GpExpressDao",
            "label": "node dao",
            "type": "server",
            "sequence_id": 3,
            "dev_language": "Node.js",
            "dev_framework": "Express",
            "description": "dao component for a NodeJs based application",
            "connector": true
        },
        {
            "component_name": "GpAngularComponent",
            "label": "angular component",
            "type": "client",
            "sequence_id": 1,
            "dev_language": "java_script",
            "dev_framework": "Angular",
            "description": "component for Angular desktop",
            "connector": true
        },
        {
            "component_name": "GpAngularService",
            "label": "angular service",
            "type": "client",
            "sequence_id": 2,
            "dev_language": "java_script",
            "dev_framework": "Angular",
            "description": "service for Angular desktop",
            "connector": true
        },
        {
            "component_name": "GpIonicAngularComponent",
            "label": "angular component",
            "type": "client",
            "sequence_id": 1,
            "dev_language": "java_script",
            "dev_framework": "Ionic Angular",
            "description": "component for ionic Angular mobile",
            "connector": true
        },
        {
            "component_name": "GpIonicAngularService",
            "label": "angular service",
            "type": "client",
            "sequence_id": 2,
            "dev_language": "java_script",
            "dev_framework": "Ionic Angular",
            "description": "service for ionic Angular mobile",
            "connector": true
        }
    ],
    "GpAppStartup": [
        {
            "component_name": "GpExpressController",
            "label": "node controller",
            "type": "server",
            "sequence_id": 1,
            "dev_language": "Node.js",
            "dev_framework": "Express",
            "description": "controller for a NodeJs server application",
            "connector": true
        },
        {
            "component_name": "GpExpressService",
            "label": "node service",
            "type": "server",
            "sequence_id": 2,
            "dev_language": "Node.js",
            "dev_framework": "Express",
            "description": "service component for a NodeJS based application",
            "connector": true
        },
        {
            "component_name": "GpExpressDao",
            "label": "node dao",
            "type": "server",
            "sequence_id": 3,
            "dev_language": "Node.js",
            "dev_framework": "Express",
            "description": "dao component for a NodeJs based application",
            "connector": true
        },
        {
            "component_name": "GpAngularComponent",
            "label": "angular component",
            "type": "client",
            "sequence_id": 1,
            "dev_language": "java_script",
            "dev_framework": "Angular",
            "description": "component for Angular desktop",
            "connector": true
        },
        {
            "component_name": "GpAngularService",
            "label": "angular service",
            "type": "client",
            "sequence_id": 2,
            "dev_language": "java_script",
            "dev_framework": "Angular",
            "description": "service for Angular desktop",
            "connector": true
        },
        {
            "component_name": "GpIonicAngularComponent",
            "label": "angular component",
            "type": "client",
            "sequence_id": 1,
            "dev_language": "java_script",
            "dev_framework": "Ionic Angular",
            "description": "component for ionic Angular mobile",
            "connector": true
        },
        {
            "component_name": "GpIonicAngularService",
            "label": "angular service",
            "type": "client",
            "sequence_id": 2,
            "dev_language": "java_script",
            "dev_framework": "Ionic Angular",
            "description": "service for ionic Angular mobile",
            "connector": true
        }
    ],
    "GpGridExportCSV": [
        {
            "component_name": "GpExpressController",
            "label": "node controller",
            "type": "server",
            "sequence_id": 1,
            "dev_language": "Node.js",
            "dev_framework": "Express",
            "description": "controller for a NodeJs server application",
            "connector": true
        },
        {
            "component_name": "GpExpressService",
            "label": "node service",
            "type": "server",
            "sequence_id": 2,
            "dev_language": "Node.js",
            "dev_framework": "Express",
            "description": "service component for a NodeJS based application",
            "connector": true
        },
        {
            "component_name": "GpExpressDao",
            "label": "node dao",
            "type": "server",
            "sequence_id": 3,
            "dev_language": "Node.js",
            "dev_framework": "Express",
            "description": "dao component for a NodeJs based application",
            "connector": true
        }
    ]
}